django_require_login/__init__.py
django_require_login/conf.py
django_require_login/decorators.py
django_require_login/exceptions.py
django_require_login/middleware.py
django_require_login/mixins.py
django_require_login/utils.py
django_require_login-1.1.4.dist-info/LICENSE.md
django_require_login-1.1.4.dist-info/METADATA
django_require_login-1.1.4.dist-info/WHEEL
django_require_login-1.1.4.dist-info/RECORD
