Metadata-Version: 2.1
Name: django-require-login
Version: 1.1.4
Summary: Middleware to require login for all Django URLs
Home-page: https://github.com/laactech/django-require-login
License: BSD-3-Clause
Keywords: django,login required,authentication,login,python
Author: Steven Pate
Author-email: steven@laac.dev
Requires-Python: >=3.10,<4.0
Classifier: Development Status :: 5 - Production/Stable
Classifier: Environment :: Web Environment
Classifier: Intended Audience :: Developers
Classifier: License :: OSI Approved :: BSD License
Classifier: Natural Language :: English
Classifier: Programming Language :: Python
Classifier: Programming Language :: Python :: 3
Classifier: Programming Language :: Python :: 3.10
Classifier: Programming Language :: Python :: 3.11
Classifier: Programming Language :: Python :: 3
Classifier: Programming Language :: Python :: 3.10
Classifier: Programming Language :: Python :: 3.11
Classifier: Programming Language :: Python :: 3.12
Requires-Dist: django (>=4.2)
Project-URL: Repository, https://github.com/laactech/django-require-login
